{
    "f1d84040-36f6-47dc-9031-4fdf4e1153bf": [
        {   "a41d84f5-d9ff-4da9-9cc0-5962336e0ef1": {
                "Thrust": [
                    {
                        "thrust": [
                            5, 8
                        ]
                    }, 
                    {
                        "thrust": [
                            5, -5
                        ]
                    }
                ], 
                "Position": [
                    {
                        "pos": [
                            920, 70
                        ]
                    }
                ], 
                "Image": [
                    {
                        "path": "banana-katana.png"
                    }
                ], 
                "Velocity": [
                    {
                        "velocity": [
                            36, 31
                        ]
                    }
                ]
            }
        }, 
        {
            "dfac61c7-3229-49ac-b824-fc9c23eb0968": {
                "Display": [
                    {
                        "width": 1280,  "height": 720
                    }
                ]
            }
        }, 
        {
            "6d77742e-5820-4ef8-836f-aa3903f035a0": {
                "Thrust": [
                    {
                        "thrust": [
                            -2, -20
                        ]
                    }, 
                    {
                        "thrust": [
                            -8, -3
                        ]
                    }
                ], 
                "Position": [
                    {
                        "pos": [
                            220, 166
                        ]
                    }
                ], 
                "Image": [
                    {
                        "path": "banana-katana.png"
                    }
                ], 
                "Velocity": [
                    {
                        "velocity": [
                            25, 22
                        ]
                    }
                ]
            }
        }, 
        {
            "515a2be6-5fc6-41b8-ab26-f926d0f7f963": {
                "Thrust": [
                    {
                        "thrust": [
                            -6, -5
                        ]
                    }, 
                    {
                        "thrust": [
                            5, -7
                        ]
                    }
                ], 
                "Position": [
                    {
                        "pos": [
                            364, 681
                        ]
                    }
                ], 
                "Image": [
                    {
                        "path": "banana-katana.png"
                    }
                ], 
                "Velocity": [
                    {
                        "velocity": [
                            -13, -20
                        ]
                    }
                ]
            }
        }, 
        {
            "2397c811-4f59-43e9-8744-52e079db6de2": {
                "Thrust": [
                    {
                        "thrust": [
                            10, 10
                        ]
                    }, 
                    {
                        "thrust": [
                            0, 14
                        ]
                    }
                ], 
                "Position": [
                    {
                        "pos": [
                            226, 134
                        ]
                    }
                ], 
                "Image": [
                    {
                        "path": "banana-katana.png"
                    }
                ], 
                "Velocity": [
                    {
                        "velocity": [
                            -23, -9
                        ]
                    }
                ]
            }
        }, 
        {
            "fe0f29d5-39a7-4f12-8893-870c16bca757": {
                "Thrust": [
                    {
                        "thrust": [
                            -7, -15
                        ]
                    }, 
                    {
                        "thrust": [
                            -2, -17
                        ]
                    }
                ], 
                "Position": [
                    {
                        "pos": [
                            609, 445
                        ]
                    }
                ], 
                "Image": [
                    {
                        "path": "banana-katana.png"
                    }
                ], 
                "Velocity": [
                    {
                        "velocity": [
                            20, 3
                        ]
                    }
                ]
            }
        }, 
        {
            "ba95d044-cc00-4cd5-8507-1cbdd3e09c00": {
                "Thrust": [
                    {
                        "thrust": [
                            9, 6
                        ]
                    }, 
                    {
                        "thrust": [
                            5, 0
                        ]
                    }
                ], 
                "Position": [
                    {
                        "pos": [
                            794, 134
                        ]
                    }
                ], 
                "Image": [
                    {
                        "path": "banana-katana.png"
                    }
                ], 
                "Velocity": [
                    {
                        "velocity": [
                            26, 26
                        ]
                    }
                ]
            }
        }, 
        {
            "ba8a7732-c011-47ce-90d5-d5cb9288f1a6": {
                "Thrust": [
                    {
                        "thrust": [
                            -7, 13
                        ]
                    }, 
                    {
                        "thrust": [
                            9, -16
                        ]
                    }
                ], 
                "Position": [
                    {
                        "pos": [
                            21, 381
                        ]
                    }
                ], 
                "Image": [
                    {
                        "path": "banana-katana.png"
                    }
                ], 
                "Velocity": [
                    {
                        "velocity": [
                            21, 5
                        ]
                    }
                ]
            }
        }, 
        {
            "1a4af403-7296-4da0-a6a1-706082d8a69c": {
                "Thrust": [
                    {
                        "thrust": [
                            -10, 5
                        ]
                    }, 
                    {
                        "thrust": [
                            -9, 5
                        ]
                    }
                ], 
                "Position": [
                    {
                        "pos": [
                            847, 57
                        ]
                    }
                ], 
                "Image": [
                    {
                        "path": "banana-katana.png"
                    }
                ], 
                "Velocity": [
                    {
                        "velocity": [
                            -40, -35
                        ]
                    }
                ]
            }
        }, 
        {
            "74fdc272-d08f-4414-b6e1-880f4e19b7ec": {
                "Thrust": [
                    {
                        "thrust": [
                            -2, 12
                        ]
                    }, 
                    {
                        "thrust": [
                            -3, -15
                        ]
                    }
                ], 
                "Position": [
                    {
                        "pos": [
                            725, 245
                        ]
                    }
                ], 
                "Image": [
                    {
                        "path": "banana-katana.png"
                    }
                ], 
                "Velocity": [
                    {
                        "velocity": [
                            30, 15
                        ]
                    }
                ]
            }
        }, 
        {
            "c5f50e2a-d34d-4e26-acc3-8c48d4ef1df9": {
                "Thrust": [
                    {
                        "thrust": [
                            -6, -17
                        ]
                    }, 
                    {
                        "thrust": [
                            0, -12
                        ]
                    }
                ], 
                "Position": [
                    {
                        "pos": [
                            1258, 436
                        ]
                    }
                ], 
                "Image": [
                    {
                        "path": "banana-katana.png"
                    }
                ], 
                "Velocity": [
                    {
                        "velocity": [
                            -16, 
                            -28
                        ]
                    }
                ]
            }
        }
    ]
}